kintyre_speedtest.py
kintyre_speedtest_agent-0.4.0.dist-info/METADATA
kintyre_speedtest_agent-0.4.0.dist-info/WHEEL
kintyre_speedtest_agent-0.4.0.dist-info/entry_points.txt
kintyre_speedtest_agent-0.4.0.dist-info/top_level.txt
kintyre_speedtest_agent-0.4.0.dist-info/RECORD
