Metadata-Version: 2.1
Name: kintyre-speedtest-agent
Version: 0.4.0
Summary: Kintyre Shinnecock speedtest agent
Home-page: https://github.com/Kintyre/shinnecock-agent
Author: Lowell Alleman
Author-email: lowell@kintyre.co
License: Apache Software License
Keywords: splunk speedtest
Platform: UNKNOWN
Classifier: Development Status :: 3 - Alpha
Classifier: Environment :: Console
Classifier: Intended Audience :: End Users/Desktop
Classifier: Intended Audience :: Information Technology
Classifier: Intended Audience :: System Administrators
Classifier: License :: OSI Approved :: Apache Software License
Classifier: Natural Language :: English
Classifier: Operating System :: MacOS :: MacOS X
Classifier: Operating System :: Microsoft :: Windows
Classifier: Operating System :: POSIX :: Linux
Classifier: Programming Language :: Python :: 2.7
Classifier: Programming Language :: Python :: 3.4
Classifier: Programming Language :: Python :: 3.5
Classifier: Programming Language :: Python :: 3.6
Classifier: Programming Language :: Python :: 3.7
Classifier: Programming Language :: Python :: 3.8
Classifier: Programming Language :: Python :: 3.9
Classifier: Topic :: Communications
Classifier: Topic :: Internet
Classifier: Topic :: System :: Networking :: Monitoring
Requires-Dist: six
Requires-Dist: speedtest-cli
Requires-Dist: ifcfg (>=0.17.0)
Requires-Dist: requests
Requires-Dist: configparser ; python_version == "2.7"
